[
  {
    "encoder_length": 10,
    "seed": 42,
    "train_accuracy": 0.7022829341317365,
    "val_accuracy": 0.6884105240269623,
    "test_accuracy": 0.6822735191637631,
    "test_precision": 0.6836734693877551,
    "test_recall": 0.7100466299279355,
    "test_f1_score": 0.6966105219380329,
    "train_samples": 21405,
    "val_samples": 4599,
    "test_samples": 4592,
    "train_matches": 21405,
    "val_matches": 4599,
    "test_matches": 4592
  },
  {
    "encoder_length": 10,
    "seed": 123,
    "train_accuracy": 0.7050898203592815,
    "val_accuracy": 0.690150032615786,
    "test_accuracy": 0.6820557491289199,
    "test_precision": 0.6977562692476903,
    "test_recall": 0.672318779143705,
    "test_f1_score": 0.6848013816925734,
    "train_samples": 21405,
    "val_samples": 4599,
    "test_samples": 4592,
    "train_matches": 21405,
    "val_matches": 4599,
    "test_matches": 4592
  },
  {
    "encoder_length": 10,
    "seed": 456,
    "train_accuracy": 0.7023297155688623,
    "val_accuracy": 0.6888454011741683,
    "test_accuracy": 0.6829268292682927,
    "test_precision": 0.6825717751718561,
    "test_recall": 0.7155574395930479,
    "test_f1_score": 0.6986754966887417,
    "train_samples": 21405,
    "val_samples": 4599,
    "test_samples": 4592,
    "train_matches": 21405,
    "val_matches": 4599,
    "test_matches": 4592
  },
  {
    "encoder_length": 10,
    "seed": 789,
    "train_accuracy": 0.7034056886227545,
    "val_accuracy": 0.6892802783213742,
    "test_accuracy": 0.6866289198606271,
    "test_precision": 0.6841473178542834,
    "test_recall": 0.7244595167443832,
    "test_f1_score": 0.7037265801935351,
    "train_samples": 21405,
    "val_samples": 4599,
    "test_samples": 4592,
    "train_matches": 21405,
    "val_matches": 4599,
    "test_matches": 4592
  },
  {
    "encoder_length": 10,
    "seed": 1011,
    "train_accuracy": 0.7071949850299402,
    "val_accuracy": 0.6888454011741683,
    "test_accuracy": 0.6833623693379791,
    "test_precision": 0.6826806620912395,
    "test_recall": 0.7168291649003815,
    "test_f1_score": 0.6993382961124897,
    "train_samples": 21405,
    "val_samples": 4599,
    "test_samples": 4592,
    "train_matches": 21405,
    "val_matches": 4599,
    "test_matches": 4592
  },
  {
    "encoder_length": 10,
    "seed": 1213,
    "train_accuracy": 0.7028443113772455,
    "val_accuracy": 0.6892802783213742,
    "test_accuracy": 0.6861933797909407,
    "test_precision": 0.6846339501206757,
    "test_recall": 0.7214921576939382,
    "test_f1_score": 0.7025799793601651,
    "train_samples": 21405,
    "val_samples": 4599,
    "test_samples": 4592,
    "train_matches": 21405,
    "val_matches": 4599,
    "test_matches": 4592
  },
  {
    "encoder_length": 10,
    "seed": 1415,
    "train_accuracy": 0.7022829341317365,
    "val_accuracy": 0.6858012611437269,
    "test_accuracy": 0.6827090592334495,
    "test_precision": 0.6760343481654957,
    "test_recall": 0.7342094107672743,
    "test_f1_score": 0.7039219670798618,
    "train_samples": 21405,
    "val_samples": 4599,
    "test_samples": 4592,
    "train_matches": 21405,
    "val_matches": 4599,
    "test_matches": 4592
  },
  {
    "encoder_length": 10,
    "seed": 1617,
    "train_accuracy": 0.7032185628742516,
    "val_accuracy": 0.6918895412046097,
    "test_accuracy": 0.6840156794425087,
    "test_precision": 0.6886949293433084,
    "test_recall": 0.7024162780839339,
    "test_f1_score": 0.6954879328436516,
    "train_samples": 21405,
    "val_samples": 4599,
    "test_samples": 4592,
    "train_matches": 21405,
    "val_matches": 4599,
    "test_matches": 4592
  },
  {
    "encoder_length": 10,
    "seed": 1819,
    "train_accuracy": 0.703125,
    "val_accuracy": 0.6908023483365949,
    "test_accuracy": 0.6861933797909407,
    "test_precision": 0.6948217317487266,
    "test_recall": 0.6939381093683764,
    "test_f1_score": 0.6943796394485684,
    "train_samples": 21405,
    "val_samples": 4599,
    "test_samples": 4592,
    "train_matches": 21405,
    "val_matches": 4599,
    "test_matches": 4592
  },
  {
    "encoder_length": 10,
    "seed": 2021,
    "train_accuracy": 0.6999906437125748,
    "val_accuracy": 0.6879756468797564,
    "test_accuracy": 0.6846689895470384,
    "test_precision": 0.7119590507212658,
    "test_recall": 0.6485799067401441,
    "test_f1_score": 0.678793256433008,
    "train_samples": 21405,
    "val_samples": 4599,
    "test_samples": 4592,
    "train_matches": 21405,
    "val_matches": 4599,
    "test_matches": 4592
  }
]